<?xml version="1.0" encoding="utf-8" ?>
<dwsync>
<file name="bootstrap-grid.css" server="infinisolutionslk.com" local="131927942975731737" remote="131966471400000000" Dst="0" />
<file name="bootstrap-grid.css.map" server="infinisolutionslk.com" local="131927942973768923" remote="131966471400000000" Dst="0" />
<file name="bootstrap-grid.min.css" server="infinisolutionslk.com" local="131927942957743855" remote="131966471400000000" Dst="0" />
<file name="bootstrap-grid.min.css.map" server="infinisolutionslk.com" local="131927942956546557" remote="131966471400000000" Dst="0" />
<file name="bootstrap-reboot.css" server="infinisolutionslk.com" local="131927942948468057" remote="131966471400000000" Dst="0" />
<file name="bootstrap-reboot.css.map" server="infinisolutionslk.com" local="131927942947549305" remote="131966471400000000" Dst="0" />
<file name="bootstrap-reboot.min.css" server="infinisolutionslk.com" local="131927942945435811" remote="131966471400000000" Dst="0" />
<file name="bootstrap-reboot.min.css.map" server="infinisolutionslk.com" local="131927942943948879" remote="131966471400000000" Dst="0" />
<file name="bootstrap.css" server="infinisolutionslk.com" local="131927942941387231" remote="131966471400000000" Dst="0" />
<file name="bootstrap.css.map" server="infinisolutionslk.com" local="131927942938923860" remote="131966472000000000" Dst="0" />
<file name="bootstrap.min.css" server="infinisolutionslk.com" local="131927942921399599" remote="131966472000000000" Dst="0" />
<file name="bootstrap.min.css.map" server="infinisolutionslk.com" local="131927942917724470" remote="131966472000000000" Dst="0" />
</dwsync>